{
    "Version": 5,
    "ElasticsearchWarning": true,
    "ResolverConfig": {
        "project": {
            "ConflictHandler": "AUTOMERGE",
            "ConflictDetection": "VERSION"
        },
        "models": {
            "Company": {
                "ConflictHandler": "AUTOMERGE",
                "ConflictDetection": "VERSION"
            },
            "User": {
                "ConflictHandler": "AUTOMERGE",
                "ConflictDetection": "VERSION"
            },
            "Emision": {
                "ConflictHandler": "AUTOMERGE",
                "ConflictDetection": "VERSION"
            },
            "Factor": {
                "ConflictHandler": "AUTOMERGE",
                "ConflictDetection": "VERSION"
            },
            "Establishment": {
                "ConflictHandler": "AUTOMERGE",
                "ConflictDetection": "VERSION"
            }
        }
    }
}